TrainingDataCreation.py
__init__.py
custom_t5_model.py
main.py
run.py
customt5-1.0.0.dist-info/METADATA
customt5-1.0.0.dist-info/WHEEL
customt5-1.0.0.dist-info/RECORD
